other_python/__init__.py
other_python/other.py
other_python/percent.py
other_python/tools.py
other_python-4.2.dist-info/LICENSE
other_python-4.2.dist-info/METADATA
other_python-4.2.dist-info/WHEEL
other_python-4.2.dist-info/top_level.txt
other_python-4.2.dist-info/RECORD
