Metadata-Version: 2.1
Name: other-python
Version: 4.2
Summary: upgraded version of calc-plus
Home-page: https://github.com/keegang6705/other-python
Author: keegang_6705
Author-email: darunphobwi@gmail.com
License: MIT
Platform: UNKNOWN
Requires-Python: >=3.0
License-File: LICENSE
